allvoicelab_mcp/__init__.py
allvoicelab_mcp/server.py
allvoicelab_mcp/tools/__init__.py
allvoicelab_mcp/tools/base.py
allvoicelab_mcp/tools/dubbing.py
allvoicelab_mcp/tools/speech.py
allvoicelab_mcp/tools/subtitle_extraction_tool.py
allvoicelab_mcp/tools/text_translation.py
allvoicelab_mcp/tools/utils.py
allvoicelab_mcp/tools/voice_info.py
allvoicelab_mcp-0.0.5.dist-info/licenses/LICENSE
client/__init__.py
client/all_voice_lab.py
client/model.py
client/__pycache__/__init__.cpython-311.pyc
client/__pycache__/__init__.cpython-312.pyc
client/__pycache__/all_voice_lab.cpython-311.pyc
client/__pycache__/all_voice_lab.cpython-312.pyc
client/__pycache__/audio_isolation.cpython-311.pyc
client/__pycache__/get_all_voices.cpython-311.pyc
client/__pycache__/get_supported_voice_model.cpython-311.pyc
client/__pycache__/model.cpython-311.pyc
client/__pycache__/model.cpython-312.pyc
client/__pycache__/speech_to_speech.cpython-311.pyc
client/__pycache__/text_to_speech.cpython-311.pyc
allvoicelab_mcp-0.0.5.dist-info/METADATA
allvoicelab_mcp-0.0.5.dist-info/WHEEL
allvoicelab_mcp-0.0.5.dist-info/entry_points.txt
allvoicelab_mcp-0.0.5.dist-info/top_level.txt
allvoicelab_mcp-0.0.5.dist-info/RECORD
