Metadata-Version: 2.4
Name: allvoicelab-mcp
Version: 0.0.5
Summary: AllVoiceLab MCP Server
Author-email: AllVoiceLab <tech@allvoicelab.com>
License: MIT License
Keywords: mcp,text-to-speech,speech-to-text,voice-cloning
Requires-Python: >=3.11
License-File: LICENSE
Requires-Dist: build>=1.2.2.post1
Requires-Dist: mcp[cli]>=1.6.0
Requires-Dist: requests>=2.32.3
Requires-Dist: setuptools>=45
Requires-Dist: twine>=6.1.0
Dynamic: license-file
